{
  "https://www.jetro.go.jp/rss/biznews.xml": {
    "etag": "\"40be-6563dace9865f-gzip\"",
    "lastModified": "Fri, 10 Jul 2026 08:39:14 GMT",
    "updatedAt": "2026-07-12T09:12:49+09:00"
  },
  "https://assets.wor.jp/rss/rdf/nikkei/news.rdf": {
    "etag": "W/\"5d1b770ac7c2eaef2c75cb38782f7b63\"",
    "lastModified": "Sat, 11 Jul 2026 22:11:11 GMT",
    "updatedAt": "2026-07-12T09:12:49+09:00"
  },
  "https://assets.wor.jp/rss/rdf/nikkei/economy.rdf": {
    "etag": "W/\"e4f942d20cb1296665d3d5575c559144\"",
    "lastModified": "Sat, 11 Jul 2026 23:12:43 GMT",
    "updatedAt": "2026-07-12T09:12:49+09:00"
  },
  "https://assets.wor.jp/rss/rdf/nikkei/business.rdf": {
    "etag": "W/\"052e98f95c5a944f021926d529dd0648\"",
    "lastModified": "Sat, 11 Jul 2026 22:13:52 GMT",
    "updatedAt": "2026-07-12T09:12:49+09:00"
  },
  "https://assets.wor.jp/rss/rdf/nikkei/markets.rdf": {
    "etag": "W/\"16381c31960e5349c00257633aa59ce6\"",
    "lastModified": "Sat, 11 Jul 2026 23:12:35 GMT",
    "updatedAt": "2026-07-12T09:12:49+09:00"
  },
  "https://www.tdb.co.jp/rss/jouhou.rdf": {
    "etag": "\"4f05-65637c0ec6b7d\"",
    "lastModified": "Fri, 10 Jul 2026 01:35:20 GMT",
    "updatedAt": "2026-07-12T09:12:49+09:00"
  },
  "https://www.tsr-net.co.jp/rss/news_status.xml": {
    "etag": "",
    "lastModified": "Sat, 11 Jul 2026 22:00:00 GMT",
    "updatedAt": "2026-07-12T09:12:50+09:00"
  },
  "https://www.tsr-net.co.jp/rss/news_flash.xml": {
    "etag": "",
    "lastModified": "Sat, 11 Jul 2026 22:00:00 GMT",
    "updatedAt": "2026-07-12T09:12:51+09:00"
  },
  "https://www.tsr-net.co.jp/rss/news.xml": {
    "etag": "",
    "lastModified": "Sat, 11 Jul 2026 22:00:00 GMT",
    "updatedAt": "2026-07-12T09:12:52+09:00"
  },
  "https://www.tsr-net.co.jp/rss/news_analysis.xml": {
    "etag": "",
    "lastModified": "Sat, 11 Jul 2026 22:00:00 GMT",
    "updatedAt": "2026-07-12T09:12:53+09:00"
  },
  "https://www.tsr-net.co.jp/rss/news_detail.xml": {
    "etag": "",
    "lastModified": "Sat, 11 Jul 2026 22:00:06 GMT",
    "updatedAt": "2026-07-12T09:12:54+09:00"
  },
  "https://www.mlit.go.jp/saigai.rdf": {
    "etag": "W/\"1439b48a72c0725d7df4e5b1e05058d5\"",
    "lastModified": "Sun, 12 Jul 2026 00:03:43 GMT",
    "updatedAt": "2026-07-12T09:12:54+09:00"
  },
  "https://www.mlit.go.jp/pressrelease.rdf": {
    "etag": "W/\"d4e7b359cf1377d80ff7fb6d4ed49bba\"",
    "lastModified": "Fri, 10 Jul 2026 08:10:08 GMT",
    "updatedAt": "2026-07-12T09:12:54+09:00"
  },
  "https://oilgas-info.jogmec.go.jp/rsslist/report_all.xml": {
    "etag": "\"1700-64c02d470b69a\"",
    "lastModified": "Mon, 02 Mar 2026 04:14:58 GMT",
    "updatedAt": "2026-03-02T15:00:42+09:00"
  },
  "https://www.customs.go.jp/news.rss": {
    "etag": "",
    "lastModified": "Fri, 10 Jul 2026 09:00:11 GMT",
    "updatedAt": "2026-07-12T09:12:55+09:00"
  },
  "https://assets.wor.jp/rss/rdf/bloomberg/opinion.rdf": {
    "etag": "W/\"800c1ae1c4e1255f3c0efb3b26c4bd75\"",
    "lastModified": "Sat, 11 Jul 2026 23:12:21 GMT",
    "updatedAt": "2026-07-12T09:12:55+09:00"
  },
  "https://assets.wor.jp/rss/rdf/bloomberg/economics.rdf": {
    "etag": "W/\"7552af5e7f6825c4ed2614a8319ea797\"",
    "lastModified": "Sat, 11 Jul 2026 23:10:23 GMT",
    "updatedAt": "2026-07-12T09:12:55+09:00"
  },
  "https://assets.wor.jp/rss/rdf/bloomberg/technology.rdf": {
    "etag": "W/\"f199aa89dfae120c7f7729e5e050a838\"",
    "lastModified": "Sat, 11 Jul 2026 23:13:44 GMT",
    "updatedAt": "2026-07-12T09:12:55+09:00"
  },
  "https://assets.wor.jp/rss/rdf/bloomberg/companies.rdf": {
    "etag": "W/\"9645b1a6dabdd8ef9519b086c6226a27\"",
    "lastModified": "Sat, 11 Jul 2026 23:10:35 GMT",
    "updatedAt": "2026-07-12T09:12:56+09:00"
  },
  "https://assets.wor.jp/rss/rdf/bloomberg/international.rdf": {
    "etag": "W/\"b2508c9854af9cd10d874a672c94e04d\"",
    "lastModified": "Sat, 11 Jul 2026 22:13:24 GMT",
    "updatedAt": "2026-07-12T09:12:56+09:00"
  },
  "https://assets.wor.jp/rss/rdf/bloomberg/finance.rdf": {
    "etag": "W/\"294e6820c5becc8029fae8b9c86f01c6\"",
    "lastModified": "Sat, 11 Jul 2026 23:12:10 GMT",
    "updatedAt": "2026-07-12T09:12:56+09:00"
  },
  "https://assets.wor.jp/rss/rdf/bloomberg/markets.rdf": {
    "etag": "W/\"01ae8e23eadbfd9946af50b56e20f292\"",
    "lastModified": "Sat, 11 Jul 2026 22:13:06 GMT",
    "updatedAt": "2026-07-12T09:12:56+09:00"
  },
  "https://assets.wor.jp/rss/rdf/reuters/opinion.rdf": {
    "etag": "W/\"22cab37a7827ca8562b4751e09e685f7\"",
    "lastModified": "Sat, 11 Jul 2026 23:13:53 GMT",
    "updatedAt": "2026-07-12T09:12:56+09:00"
  },
  "https://assets.wor.jp/rss/rdf/reuters/business.rdf": {
    "etag": "\"07d7e87a3f1d22ceca7f55d6b4c002c8\"",
    "lastModified": "Sat, 13 Jun 2026 06:12:59 GMT",
    "updatedAt": "2026-07-12T09:12:56+09:00"
  },
  "https://assets.wor.jp/rss/rdf/reuters/economy.rdf": {
    "etag": "W/\"1513f59a3aadc7b675198ce68a27dae6\"",
    "lastModified": "Sat, 11 Jul 2026 22:13:47 GMT",
    "updatedAt": "2026-07-12T09:12:57+09:00"
  },
  "https://assets.wor.jp/rss/rdf/reuters/markets.rdf": {
    "etag": "\"9a90d0f47f6165b882ff487fe96d9e7b\"",
    "lastModified": "Wed, 08 Jul 2026 13:16:24 GMT",
    "updatedAt": "2026-07-12T09:12:57+09:00"
  },
  "https://assets.wor.jp/rss/rdf/reuters/world.rdf": {
    "etag": "W/\"15e1d3f66b4a7a93134a17365ff47c05\"",
    "lastModified": "Sat, 11 Jul 2026 22:11:37 GMT",
    "updatedAt": "2026-07-12T09:12:57+09:00"
  },
  "https://assets.wor.jp/rss/rdf/reuters/top.rdf": {
    "etag": "W/\"61d29819373e24bb585e17e001b4056b\"",
    "lastModified": "Sat, 11 Jul 2026 22:12:09 GMT",
    "updatedAt": "2026-07-12T09:12:57+09:00"
  },
  "https://www.cao.go.jp/rss/news.rdf": {
    "etag": "W/\"19d1-6563bc2efb327\"",
    "lastModified": "Fri, 10 Jul 2026 06:22:13 GMT",
    "updatedAt": "2026-07-12T09:12:58+09:00"
  },
  "https://www.mof.go.jp/rss/index.xml": {
    "etag": "\"4d71-61c7f0b897cb3\"",
    "lastModified": "Fri, 05 Jul 2024 12:17:20 GMT",
    "updatedAt": "2026-03-05T01:07:36+09:00"
  },
  "https://earthquake.usgs.gov/earthquakes/feed/v1.0/summary/all_hour.atom": {
    "etag": "",
    "lastModified": "Sun, 12 Jul 2026 00:12:00 GMT",
    "updatedAt": "2026-07-12T09:12:58+09:00"
  },
  "https://www.eia.gov/rss/todayinenergy.xml": {
    "etag": "\"80b994f2a0fdd1:0\"",
    "lastModified": "Thu, 09 Jul 2026 12:46:23 GMT",
    "updatedAt": "2026-07-12T09:12:58+09:00"
  },
  "https://www.gdacs.org/xml/rss.xml": {
    "etag": "\"ec20a51b9211dd1:0\"",
    "lastModified": "Sun, 12 Jul 2026 00:05:11 GMT",
    "updatedAt": "2026-07-12T09:13:00+09:00"
  },
  "https://www.freightwaves.com/rss": {
    "etag": "\"748c948636306c7a1c51aec264c8c095\"",
    "lastModified": "Sat, 11 Jul 2026 16:33:13 GMT",
    "updatedAt": "2026-07-12T09:13:01+09:00"
  },
  "https://www.supplychaindive.com/feeds/news/": {
    "etag": "",
    "lastModified": "Fri, 10 Jul 2026 15:10:42 GMT",
    "updatedAt": "2026-07-12T09:13:01+09:00"
  },
  "https://www.digitimes.com/rss/daily.xml": {
    "etag": "W/\"4cc8c6639111dd1:0\"",
    "lastModified": "Sun, 12 Jul 2026 00:00:03 GMT",
    "updatedAt": "2026-07-12T09:13:01+09:00"
  },
  "https://www.eetimes.com/feed/": {
    "etag": "W/\"953449e370ef30c24a04f8219e0e71a3\"",
    "lastModified": "Fri, 19 Jun 2026 08:39:57 GMT",
    "updatedAt": "2026-06-19T21:18:55+09:00"
  },
  "https://semiengineering.com/feed/": {
    "etag": "\"32253d5f278fc3043fb433f8783c37f6\"",
    "lastModified": "Fri, 10 Jul 2026 16:54:57 GMT",
    "updatedAt": "2026-07-12T09:13:02+09:00"
  },
  "https://www.fca.org.uk/news/rss.xml": {
    "etag": "W/\"1783813847\"",
    "lastModified": "Sat, 11 Jul 2026 23:50:47 GMT",
    "updatedAt": "2026-07-12T09:13:03+09:00"
  },
  "https://www.gov.uk/government/organisations/export-control-joint-unit.atom": {
    "etag": "W/\"57c3d54137fb0cfae15bd53412001f3e\"",
    "lastModified": "",
    "updatedAt": "2026-07-12T09:13:05+09:00"
  },
  "https://agenciabrasil.ebc.com.br/rss.xml": {
    "etag": "\"1781871265-1\"",
    "lastModified": "Fri, 19 Jun 2026 12:14:25 GMT",
    "updatedAt": "2026-06-19T21:18:59+09:00"
  },
  "https://www.spa.gov.sa/rss.xml": {
    "etag": "\"ff7df7-0bbeb2504418\"",
    "lastModified": "",
    "updatedAt": "2026-03-08T23:57:27+09:00"
  },
  "https://www.gov.sg/rss/": {
    "etag": "W/\"ad8306d6174a1de6e23fbca4743e0344\"",
    "lastModified": "Thu, 04 Jun 2026 11:07:35 GMT",
    "updatedAt": "2026-06-19T21:19:03+09:00"
  },
  "https://www.gov.uk/government/organisations/department-for-transport.atom": {
    "etag": "W/\"7e0f8269c7d23937a408fec68a630d2b\"",
    "lastModified": "",
    "updatedAt": "2026-07-12T09:13:05+09:00"
  },
  "https://www.euronews.com/rss": {
    "etag": "\"1fffeff922275cf9136c2e258837f1ed-gzip\"",
    "lastModified": "Sat, 11 Jul 2026 20:03:37 GMT",
    "updatedAt": "2026-07-12T09:13:05+09:00"
  },
  "https://www.mof.go.jp/news.rss": {
    "etag": "\"7164-65642fc883054\"",
    "lastModified": "Fri, 10 Jul 2026 14:59:24 GMT",
    "updatedAt": "2026-07-12T09:13:06+09:00"
  },
  "https://www.semi.org/en/rss.xml": {
    "etag": "W/\"1781870654\"",
    "lastModified": "Fri, 19 Jun 2026 12:04:14 GMT",
    "updatedAt": "2026-06-19T21:18:54+09:00"
  }
}