{
  "https://www.jetro.go.jp/rss/biznews.xml": {
    "etag": "\"3eb8-652066bdbebfa-gzip\"",
    "lastModified": "Sun, 17 May 2026 17:03:13 GMT",
    "updatedAt": "2026-05-18T13:44:10+09:00"
  },
  "https://assets.wor.jp/rss/rdf/nikkei/news.rdf": {
    "etag": "W/\"cabae0f6a228ed97ef00135fcd89369e\"",
    "lastModified": "Mon, 18 May 2026 04:10:55 GMT",
    "updatedAt": "2026-05-18T13:44:11+09:00"
  },
  "https://assets.wor.jp/rss/rdf/nikkei/economy.rdf": {
    "etag": "W/\"bec44f8c0a8e8aa179cd98f705ba3ca8\"",
    "lastModified": "Mon, 18 May 2026 02:12:22 GMT",
    "updatedAt": "2026-05-18T13:44:11+09:00"
  },
  "https://assets.wor.jp/rss/rdf/nikkei/business.rdf": {
    "etag": "W/\"961e998d66167c7908404826e38171c7\"",
    "lastModified": "Mon, 18 May 2026 02:10:15 GMT",
    "updatedAt": "2026-05-18T13:44:11+09:00"
  },
  "https://assets.wor.jp/rss/rdf/nikkei/markets.rdf": {
    "etag": "W/\"e101c7bae810af5aa835f589a1b58976\"",
    "lastModified": "Mon, 18 May 2026 03:13:07 GMT",
    "updatedAt": "2026-05-18T13:44:11+09:00"
  },
  "https://www.tdb.co.jp/rss/jouhou.rdf": {
    "etag": "\"4df0-651d27e28b0f5\"",
    "lastModified": "Fri, 15 May 2026 03:06:01 GMT",
    "updatedAt": "2026-05-18T13:44:11+09:00"
  },
  "https://www.tsr-net.co.jp/rss/news_status.xml": {
    "etag": "",
    "lastModified": "Mon, 18 May 2026 03:55:02 GMT",
    "updatedAt": "2026-05-18T13:44:11+09:00"
  },
  "https://www.tsr-net.co.jp/rss/news_flash.xml": {
    "etag": "",
    "lastModified": "Mon, 18 May 2026 03:55:02 GMT",
    "updatedAt": "2026-05-18T13:44:12+09:00"
  },
  "https://www.tsr-net.co.jp/rss/news.xml": {
    "etag": "",
    "lastModified": "Mon, 18 May 2026 03:55:02 GMT",
    "updatedAt": "2026-05-18T13:44:13+09:00"
  },
  "https://www.tsr-net.co.jp/rss/news_analysis.xml": {
    "etag": "",
    "lastModified": "Mon, 18 May 2026 03:55:02 GMT",
    "updatedAt": "2026-05-18T13:44:13+09:00"
  },
  "https://www.tsr-net.co.jp/rss/news_detail.xml": {
    "etag": "",
    "lastModified": "Mon, 18 May 2026 03:55:06 GMT",
    "updatedAt": "2026-05-18T13:44:14+09:00"
  },
  "https://www.mlit.go.jp/saigai.rdf": {
    "etag": "W/\"7e636da212145c3b8d97a1d9ad2eb380\"",
    "lastModified": "Fri, 15 May 2026 13:31:08 GMT",
    "updatedAt": "2026-05-18T13:44:15+09:00"
  },
  "https://www.mlit.go.jp/pressrelease.rdf": {
    "etag": "W/\"78068e746f77c110108d15c51eb54f98\"",
    "lastModified": "Fri, 15 May 2026 13:49:35 GMT",
    "updatedAt": "2026-05-18T13:44:15+09:00"
  },
  "https://oilgas-info.jogmec.go.jp/rsslist/report_all.xml": {
    "etag": "\"1700-64c02d470b69a\"",
    "lastModified": "Mon, 02 Mar 2026 04:14:58 GMT",
    "updatedAt": "2026-03-02T15:00:42+09:00"
  },
  "https://www.customs.go.jp/news.rss": {
    "etag": "",
    "lastModified": "Mon, 18 May 2026 01:14:33 GMT",
    "updatedAt": "2026-05-18T13:44:15+09:00"
  },
  "https://assets.wor.jp/rss/rdf/bloomberg/opinion.rdf": {
    "etag": "W/\"3b6029af694735274f9142ae37e9c06c\"",
    "lastModified": "Mon, 18 May 2026 02:14:45 GMT",
    "updatedAt": "2026-05-18T13:44:15+09:00"
  },
  "https://assets.wor.jp/rss/rdf/bloomberg/economics.rdf": {
    "etag": "W/\"984a8f953422c018f3f07dd48682241f\"",
    "lastModified": "Mon, 18 May 2026 03:14:58 GMT",
    "updatedAt": "2026-05-18T13:44:15+09:00"
  },
  "https://assets.wor.jp/rss/rdf/bloomberg/technology.rdf": {
    "etag": "W/\"b10ca80ea8eb7b380f77caa9948b5bf5\"",
    "lastModified": "Mon, 18 May 2026 04:13:42 GMT",
    "updatedAt": "2026-05-18T13:44:15+09:00"
  },
  "https://assets.wor.jp/rss/rdf/bloomberg/companies.rdf": {
    "etag": "W/\"ecc384e789bb782d1586dde4f2319b04\"",
    "lastModified": "Mon, 18 May 2026 03:12:20 GMT",
    "updatedAt": "2026-05-18T13:44:15+09:00"
  },
  "https://assets.wor.jp/rss/rdf/bloomberg/international.rdf": {
    "etag": "W/\"f5eb1e6b0d84ea6aaad0252ab924ee9b\"",
    "lastModified": "Mon, 18 May 2026 04:13:29 GMT",
    "updatedAt": "2026-05-18T13:44:15+09:00"
  },
  "https://assets.wor.jp/rss/rdf/bloomberg/finance.rdf": {
    "etag": "W/\"c4477b94e040db078226f6561ecdec67\"",
    "lastModified": "Mon, 18 May 2026 03:14:35 GMT",
    "updatedAt": "2026-05-18T13:44:16+09:00"
  },
  "https://assets.wor.jp/rss/rdf/bloomberg/markets.rdf": {
    "etag": "W/\"715df98e1f2c8826f24a06f6cf08de3a\"",
    "lastModified": "Mon, 18 May 2026 03:11:52 GMT",
    "updatedAt": "2026-05-18T13:44:16+09:00"
  },
  "https://assets.wor.jp/rss/rdf/reuters/opinion.rdf": {
    "etag": "W/\"3471d28c81e911f3fd24f61150aded99\"",
    "lastModified": "Mon, 18 May 2026 03:13:29 GMT",
    "updatedAt": "2026-05-18T13:44:16+09:00"
  },
  "https://assets.wor.jp/rss/rdf/reuters/business.rdf": {
    "etag": "W/\"f86a4ba07abeb774657b41d4d7e616d2\"",
    "lastModified": "Mon, 18 May 2026 04:13:12 GMT",
    "updatedAt": "2026-05-18T13:44:16+09:00"
  },
  "https://assets.wor.jp/rss/rdf/reuters/economy.rdf": {
    "etag": "W/\"4d2da2014b8c088cab78fdc1e3935380\"",
    "lastModified": "Mon, 18 May 2026 04:14:11 GMT",
    "updatedAt": "2026-05-18T13:44:16+09:00"
  },
  "https://assets.wor.jp/rss/rdf/reuters/markets.rdf": {
    "etag": "W/\"54516a948509affa84411ffe330c24a8\"",
    "lastModified": "Mon, 18 May 2026 03:11:38 GMT",
    "updatedAt": "2026-05-18T13:44:16+09:00"
  },
  "https://assets.wor.jp/rss/rdf/reuters/world.rdf": {
    "etag": "W/\"777c8beb0c21e00e948cd51ee07baac0\"",
    "lastModified": "Mon, 18 May 2026 04:13:54 GMT",
    "updatedAt": "2026-05-18T13:44:16+09:00"
  },
  "https://assets.wor.jp/rss/rdf/reuters/top.rdf": {
    "etag": "W/\"cd503b29cf63dcc0407cd1094313f15e\"",
    "lastModified": "Mon, 18 May 2026 03:14:44 GMT",
    "updatedAt": "2026-05-18T13:44:16+09:00"
  },
  "https://www.cao.go.jp/rss/news.rdf": {
    "etag": "W/\"19bb-651d081249940\"",
    "lastModified": "Fri, 15 May 2026 00:43:41 GMT",
    "updatedAt": "2026-05-18T13:44:17+09:00"
  },
  "https://www.mof.go.jp/rss/index.xml": {
    "etag": "\"4d71-61c7f0b897cb3\"",
    "lastModified": "Fri, 05 Jul 2024 12:17:20 GMT",
    "updatedAt": "2026-03-05T01:07:36+09:00"
  },
  "https://earthquake.usgs.gov/earthquakes/feed/v1.0/summary/all_hour.atom": {
    "etag": "",
    "lastModified": "Mon, 18 May 2026 04:44:17 GMT",
    "updatedAt": "2026-05-18T13:44:17+09:00"
  },
  "https://www.eia.gov/rss/todayinenergy.xml": {
    "etag": "\"085a05369e4dc1:0\"",
    "lastModified": "Fri, 15 May 2026 12:49:54 GMT",
    "updatedAt": "2026-05-18T13:44:17+09:00"
  },
  "https://www.gdacs.org/xml/rss.xml": {
    "etag": "\"8ca95eb37fe6dc1:0\"",
    "lastModified": "Mon, 18 May 2026 04:35:05 GMT",
    "updatedAt": "2026-05-18T13:44:19+09:00"
  },
  "https://www.freightwaves.com/rss": {
    "etag": "\"1f8b971f23f04277d27f878a921c9007\"",
    "lastModified": "Sun, 17 May 2026 18:48:52 GMT",
    "updatedAt": "2026-05-18T13:44:20+09:00"
  },
  "https://www.supplychaindive.com/feeds/news/": {
    "etag": "",
    "lastModified": "Fri, 15 May 2026 14:49:00 GMT",
    "updatedAt": "2026-05-18T13:44:20+09:00"
  },
  "https://www.digitimes.com/rss/daily.xml": {
    "etag": "W/\"266d837080e6dc1:0\"",
    "lastModified": "Mon, 18 May 2026 04:40:23 GMT",
    "updatedAt": "2026-05-18T13:44:21+09:00"
  },
  "https://www.eetimes.com/feed/": {
    "etag": "W/\"af4759a058dbcbb57e433a3cb99a58a8\"",
    "lastModified": "Sat, 28 Mar 2026 11:30:11 GMT",
    "updatedAt": "2026-03-29T10:04:17+09:00"
  },
  "https://semiengineering.com/feed/": {
    "etag": "\"3bf44da3260c7135834f2656ddaa31ea\"",
    "lastModified": "Sun, 17 May 2026 19:19:28 GMT",
    "updatedAt": "2026-05-18T13:44:22+09:00"
  },
  "https://www.fca.org.uk/news/rss.xml": {
    "etag": "W/\"1779077176\"",
    "lastModified": "Mon, 18 May 2026 04:06:16 GMT",
    "updatedAt": "2026-05-18T13:44:22+09:00"
  },
  "https://www.gov.uk/government/organisations/export-control-joint-unit.atom": {
    "etag": "W/\"8e0d758f79a1fa158b1e811b11d0c039\"",
    "lastModified": "",
    "updatedAt": "2026-05-18T13:44:25+09:00"
  },
  "https://agenciabrasil.ebc.com.br/rss.xml": {
    "etag": "\"1772981377-1\"",
    "lastModified": "Sun, 08 Mar 2026 14:49:37 GMT",
    "updatedAt": "2026-03-08T23:57:05+09:00"
  },
  "https://www.spa.gov.sa/rss.xml": {
    "etag": "\"ff7df7-0bbeb2504418\"",
    "lastModified": "",
    "updatedAt": "2026-03-08T23:57:27+09:00"
  },
  "https://www.gov.sg/rss/": {
    "etag": "W/\"4728eea38e81188bec69882cd30eeef4\"",
    "lastModified": "Fri, 06 Mar 2026 09:23:30 GMT",
    "updatedAt": "2026-03-08T22:22:32+09:00"
  },
  "https://www.gov.uk/government/organisations/department-for-transport.atom": {
    "etag": "W/\"cf8d4d8120290a335286dc9c7e62dc69\"",
    "lastModified": "",
    "updatedAt": "2026-05-18T13:44:26+09:00"
  },
  "https://www.euronews.com/rss": {
    "etag": "\"49b3f422757db66a2ee86d38e5c563cf\"",
    "lastModified": "Mon, 18 May 2026 04:23:53 GMT",
    "updatedAt": "2026-05-18T13:44:26+09:00"
  },
  "https://www.mof.go.jp/news.rss": {
    "etag": "\"74aa-6520f0bd8ab40\"",
    "lastModified": "Mon, 18 May 2026 03:20:37 GMT",
    "updatedAt": "2026-05-18T13:44:27+09:00"
  }
}