{
  "https://www.jetro.go.jp/rss/biznews.xml": {
    "etag": "\"3f95-652a0ae84a324-gzip\"",
    "lastModified": "Mon, 25 May 2026 09:05:36 GMT",
    "updatedAt": "2026-05-27T02:36:52+09:00"
  },
  "https://assets.wor.jp/rss/rdf/nikkei/news.rdf": {
    "etag": "W/\"655d5ae18cc91ca816629be699ed8467\"",
    "lastModified": "Tue, 26 May 2026 17:12:50 GMT",
    "updatedAt": "2026-05-27T02:36:54+09:00"
  },
  "https://assets.wor.jp/rss/rdf/nikkei/economy.rdf": {
    "etag": "W/\"08321903bd23ecee53a531542f068c74\"",
    "lastModified": "Tue, 26 May 2026 16:10:12 GMT",
    "updatedAt": "2026-05-27T02:36:55+09:00"
  },
  "https://assets.wor.jp/rss/rdf/nikkei/business.rdf": {
    "etag": "W/\"6950bdbc839f39e256d2ce07662e7335\"",
    "lastModified": "Tue, 26 May 2026 16:13:56 GMT",
    "updatedAt": "2026-05-27T02:36:55+09:00"
  },
  "https://assets.wor.jp/rss/rdf/nikkei/markets.rdf": {
    "etag": "W/\"82df2df4b0b7a1c331bae7c6f70709cb\"",
    "lastModified": "Tue, 26 May 2026 15:13:25 GMT",
    "updatedAt": "2026-05-27T02:36:55+09:00"
  },
  "https://www.tdb.co.jp/rss/jouhou.rdf": {
    "etag": "\"4e0b-65299e443cd9b\"",
    "lastModified": "Mon, 25 May 2026 00:59:33 GMT",
    "updatedAt": "2026-05-27T02:36:54+09:00"
  },
  "https://www.tsr-net.co.jp/rss/news_status.xml": {
    "etag": "",
    "lastModified": "Tue, 26 May 2026 15:05:14 GMT",
    "updatedAt": "2026-05-27T02:36:55+09:00"
  },
  "https://www.tsr-net.co.jp/rss/news_flash.xml": {
    "etag": "",
    "lastModified": "Tue, 26 May 2026 15:05:14 GMT",
    "updatedAt": "2026-05-27T02:36:56+09:00"
  },
  "https://www.tsr-net.co.jp/rss/news.xml": {
    "etag": "",
    "lastModified": "Tue, 26 May 2026 15:05:14 GMT",
    "updatedAt": "2026-05-27T02:36:57+09:00"
  },
  "https://www.tsr-net.co.jp/rss/news_analysis.xml": {
    "etag": "",
    "lastModified": "Tue, 26 May 2026 15:05:14 GMT",
    "updatedAt": "2026-05-27T02:36:57+09:00"
  },
  "https://www.tsr-net.co.jp/rss/news_detail.xml": {
    "etag": "",
    "lastModified": "Tue, 26 May 2026 15:05:20 GMT",
    "updatedAt": "2026-05-27T02:36:58+09:00"
  },
  "https://www.mlit.go.jp/saigai.rdf": {
    "etag": "\"92fdf4e022a4ef87f48d89c4d1b9cec5\"",
    "lastModified": "Wed, 20 May 2026 04:29:08 GMT",
    "updatedAt": "2026-05-27T02:37:00+09:00"
  },
  "https://www.mlit.go.jp/pressrelease.rdf": {
    "etag": "W/\"e215c00602ada638a8fc9fe20a22360b\"",
    "lastModified": "Tue, 26 May 2026 05:22:00 GMT",
    "updatedAt": "2026-05-27T02:37:00+09:00"
  },
  "https://oilgas-info.jogmec.go.jp/rsslist/report_all.xml": {
    "etag": "\"1700-64c02d470b69a\"",
    "lastModified": "Mon, 02 Mar 2026 04:14:58 GMT",
    "updatedAt": "2026-03-02T15:00:42+09:00"
  },
  "https://www.customs.go.jp/news.rss": {
    "etag": "",
    "lastModified": "Tue, 26 May 2026 00:00:37 GMT",
    "updatedAt": "2026-05-27T02:37:01+09:00"
  },
  "https://assets.wor.jp/rss/rdf/bloomberg/opinion.rdf": {
    "etag": "W/\"7a65bc4e84f2eca078bfda2aa4134bc3\"",
    "lastModified": "Tue, 26 May 2026 17:14:56 GMT",
    "updatedAt": "2026-05-27T02:37:02+09:00"
  },
  "https://assets.wor.jp/rss/rdf/bloomberg/economics.rdf": {
    "etag": "W/\"38fd5c7a6c63f4b11ccf86c844f2bb78\"",
    "lastModified": "Tue, 26 May 2026 16:12:29 GMT",
    "updatedAt": "2026-05-27T02:37:02+09:00"
  },
  "https://assets.wor.jp/rss/rdf/bloomberg/technology.rdf": {
    "etag": "W/\"95b4e6963767acbbb9c92fc8d7d7cf17\"",
    "lastModified": "Tue, 26 May 2026 17:10:48 GMT",
    "updatedAt": "2026-05-27T02:37:03+09:00"
  },
  "https://assets.wor.jp/rss/rdf/bloomberg/companies.rdf": {
    "etag": "W/\"3d7f063961a532d99aea21d3d5903c6b\"",
    "lastModified": "Tue, 26 May 2026 17:14:16 GMT",
    "updatedAt": "2026-05-27T02:37:03+09:00"
  },
  "https://assets.wor.jp/rss/rdf/bloomberg/international.rdf": {
    "etag": "W/\"9cbed7a1d303450b377c716b62ac840f\"",
    "lastModified": "Tue, 26 May 2026 17:12:01 GMT",
    "updatedAt": "2026-05-27T02:37:04+09:00"
  },
  "https://assets.wor.jp/rss/rdf/bloomberg/finance.rdf": {
    "etag": "W/\"618e5e07b8ef929c022468dd830be7e7\"",
    "lastModified": "Tue, 26 May 2026 17:11:31 GMT",
    "updatedAt": "2026-05-27T02:37:05+09:00"
  },
  "https://assets.wor.jp/rss/rdf/bloomberg/markets.rdf": {
    "etag": "W/\"a26c8b29e637f2f2017880dd69a5ef90\"",
    "lastModified": "Tue, 26 May 2026 17:14:42 GMT",
    "updatedAt": "2026-05-27T02:37:06+09:00"
  },
  "https://assets.wor.jp/rss/rdf/reuters/opinion.rdf": {
    "etag": "W/\"8314dac954f90b9c9f654fa721b3bdd5\"",
    "lastModified": "Tue, 26 May 2026 17:12:23 GMT",
    "updatedAt": "2026-05-27T02:37:06+09:00"
  },
  "https://assets.wor.jp/rss/rdf/reuters/business.rdf": {
    "etag": "W/\"67835f0c071fdb9a225981f0e54276f8\"",
    "lastModified": "Tue, 26 May 2026 16:11:45 GMT",
    "updatedAt": "2026-05-27T02:37:06+09:00"
  },
  "https://assets.wor.jp/rss/rdf/reuters/economy.rdf": {
    "etag": "W/\"c662fecdb904c2150fe7fe510cde2510\"",
    "lastModified": "Tue, 26 May 2026 17:10:24 GMT",
    "updatedAt": "2026-05-27T02:37:07+09:00"
  },
  "https://assets.wor.jp/rss/rdf/reuters/markets.rdf": {
    "etag": "W/\"d3cc15c5be3efe8a078c3c67b52a5020\"",
    "lastModified": "Tue, 26 May 2026 17:11:06 GMT",
    "updatedAt": "2026-05-27T02:37:08+09:00"
  },
  "https://assets.wor.jp/rss/rdf/reuters/world.rdf": {
    "etag": "W/\"9de00e4cc4d2e4199a4fae36b0d78db4\"",
    "lastModified": "Tue, 26 May 2026 16:15:02 GMT",
    "updatedAt": "2026-05-27T02:37:08+09:00"
  },
  "https://assets.wor.jp/rss/rdf/reuters/top.rdf": {
    "etag": "W/\"7e97596b8bd1b12ebe46d84e942ef594\"",
    "lastModified": "Tue, 26 May 2026 16:11:56 GMT",
    "updatedAt": "2026-05-27T02:37:08+09:00"
  },
  "https://www.cao.go.jp/rss/news.rdf": {
    "etag": "W/\"18f6-652b46bdf723f\"",
    "lastModified": "Tue, 26 May 2026 08:38:37 GMT",
    "updatedAt": "2026-05-27T02:37:10+09:00"
  },
  "https://www.mof.go.jp/rss/index.xml": {
    "etag": "\"4d71-61c7f0b897cb3\"",
    "lastModified": "Fri, 05 Jul 2024 12:17:20 GMT",
    "updatedAt": "2026-03-05T01:07:36+09:00"
  },
  "https://earthquake.usgs.gov/earthquakes/feed/v1.0/summary/all_hour.atom": {
    "etag": "",
    "lastModified": "Tue, 26 May 2026 17:36:59 GMT",
    "updatedAt": "2026-05-27T02:37:10+09:00"
  },
  "https://www.eia.gov/rss/todayinenergy.xml": {
    "etag": "\"80567780beddc1:0\"",
    "lastModified": "Tue, 26 May 2026 12:30:57 GMT",
    "updatedAt": "2026-05-27T02:37:10+09:00"
  },
  "https://www.gdacs.org/xml/rss.xml": {
    "etag": "W/\"4250c4fc35eddc1:0\"",
    "lastModified": "Tue, 26 May 2026 17:35:04 GMT",
    "updatedAt": "2026-05-27T02:37:11+09:00"
  },
  "https://www.freightwaves.com/rss": {
    "etag": "W/\"fe2bcdf02bde013d638e2ebaff44ede9\"",
    "lastModified": "Tue, 26 May 2026 17:01:42 GMT",
    "updatedAt": "2026-05-27T02:37:12+09:00"
  },
  "https://www.supplychaindive.com/feeds/news/": {
    "etag": "",
    "lastModified": "Tue, 26 May 2026 15:03:00 GMT",
    "updatedAt": "2026-05-27T02:37:13+09:00"
  },
  "https://www.digitimes.com/rss/daily.xml": {
    "etag": "W/\"980e31831eddc1:0\"",
    "lastModified": "Tue, 26 May 2026 17:00:04 GMT",
    "updatedAt": "2026-05-27T02:37:13+09:00"
  },
  "https://www.eetimes.com/feed/": {
    "etag": "W/\"af4759a058dbcbb57e433a3cb99a58a8\"",
    "lastModified": "Sat, 28 Mar 2026 11:30:11 GMT",
    "updatedAt": "2026-03-29T10:04:17+09:00"
  },
  "https://semiengineering.com/feed/": {
    "etag": "W/\"7cdf59ca4c1424565e8ad400d3401285\"",
    "lastModified": "Tue, 26 May 2026 14:50:46 GMT",
    "updatedAt": "2026-05-27T02:37:14+09:00"
  },
  "https://www.fca.org.uk/news/rss.xml": {
    "etag": "W/\"1779816781\"",
    "lastModified": "Tue, 26 May 2026 17:33:01 GMT",
    "updatedAt": "2026-05-27T02:37:15+09:00"
  },
  "https://www.gov.uk/government/organisations/export-control-joint-unit.atom": {
    "etag": "W/\"2bbc926a27316117cfe073840f623ae4\"",
    "lastModified": "",
    "updatedAt": "2026-05-27T02:37:17+09:00"
  },
  "https://agenciabrasil.ebc.com.br/rss.xml": {
    "etag": "\"1772981377-1\"",
    "lastModified": "Sun, 08 Mar 2026 14:49:37 GMT",
    "updatedAt": "2026-03-08T23:57:05+09:00"
  },
  "https://www.spa.gov.sa/rss.xml": {
    "etag": "\"ff7df7-0bbeb2504418\"",
    "lastModified": "",
    "updatedAt": "2026-03-08T23:57:27+09:00"
  },
  "https://www.gov.sg/rss/": {
    "etag": "W/\"4728eea38e81188bec69882cd30eeef4\"",
    "lastModified": "Fri, 06 Mar 2026 09:23:30 GMT",
    "updatedAt": "2026-03-08T22:22:32+09:00"
  },
  "https://www.gov.uk/government/organisations/department-for-transport.atom": {
    "etag": "W/\"46b0f64d5e0f068b3452b11f4f3f9722\"",
    "lastModified": "",
    "updatedAt": "2026-05-27T02:37:18+09:00"
  },
  "https://www.euronews.com/rss": {
    "etag": "\"9a919af4d51de2685e051d41ac7464a8\"",
    "lastModified": "Tue, 26 May 2026 16:52:29 GMT",
    "updatedAt": "2026-05-27T02:37:18+09:00"
  },
  "https://www.mof.go.jp/news.rss": {
    "etag": "\"75a9-652b48e85fac0\"",
    "lastModified": "Tue, 26 May 2026 08:48:19 GMT",
    "updatedAt": "2026-05-27T02:37:18+09:00"
  }
}