{
  "https://www.jetro.go.jp/rss/biznews.xml": {
    "etag": "\"3f22-6510e04a51236-gzip\"",
    "lastModified": "Tue, 05 May 2026 08:41:49 GMT",
    "updatedAt": "2026-05-07T19:36:04+09:00"
  },
  "https://assets.wor.jp/rss/rdf/nikkei/news.rdf": {
    "etag": "W/\"52ba738eac225a3dc003d5e5320cb93d\"",
    "lastModified": "Thu, 07 May 2026 09:10:28 GMT",
    "updatedAt": "2026-05-07T19:36:05+09:00"
  },
  "https://assets.wor.jp/rss/rdf/nikkei/economy.rdf": {
    "etag": "W/\"69c65b0490772d14af15d906404e29b5\"",
    "lastModified": "Thu, 07 May 2026 08:15:53 GMT",
    "updatedAt": "2026-05-07T19:36:05+09:00"
  },
  "https://assets.wor.jp/rss/rdf/nikkei/business.rdf": {
    "etag": "W/\"94278234b8518be3e2a65051b1b466a9\"",
    "lastModified": "Thu, 07 May 2026 10:12:05 GMT",
    "updatedAt": "2026-05-07T19:36:05+09:00"
  },
  "https://assets.wor.jp/rss/rdf/nikkei/markets.rdf": {
    "etag": "W/\"2908738ea45dce8afc8b29d936b9f7dd\"",
    "lastModified": "Thu, 07 May 2026 08:12:16 GMT",
    "updatedAt": "2026-05-07T19:36:05+09:00"
  },
  "https://www.tdb.co.jp/rss/jouhou.rdf": {
    "etag": "\"4e15-650be41babefa\"",
    "lastModified": "Fri, 01 May 2026 09:32:17 GMT",
    "updatedAt": "2026-05-07T19:36:04+09:00"
  },
  "https://www.tsr-net.co.jp/rss/news_status.xml": {
    "etag": "",
    "lastModified": "Thu, 07 May 2026 03:55:02 GMT",
    "updatedAt": "2026-05-07T13:07:36+09:00"
  },
  "https://www.tsr-net.co.jp/rss/news_flash.xml": {
    "etag": "",
    "lastModified": "Thu, 07 May 2026 03:55:02 GMT",
    "updatedAt": "2026-05-07T13:07:36+09:00"
  },
  "https://www.tsr-net.co.jp/rss/news.xml": {
    "etag": "",
    "lastModified": "Thu, 07 May 2026 03:55:02 GMT",
    "updatedAt": "2026-05-07T13:07:37+09:00"
  },
  "https://www.tsr-net.co.jp/rss/news_analysis.xml": {
    "etag": "",
    "lastModified": "Thu, 07 May 2026 03:55:02 GMT",
    "updatedAt": "2026-05-07T13:07:38+09:00"
  },
  "https://www.tsr-net.co.jp/rss/news_detail.xml": {
    "etag": "",
    "lastModified": "Thu, 07 May 2026 03:55:06 GMT",
    "updatedAt": "2026-05-07T13:07:39+09:00"
  },
  "https://www.mlit.go.jp/saigai.rdf": {
    "etag": "\"cabe37b4a95f59ee3707448db4cd9755\"",
    "lastModified": "Fri, 01 May 2026 09:00:30 GMT",
    "updatedAt": "2026-05-07T19:36:10+09:00"
  },
  "https://www.mlit.go.jp/pressrelease.rdf": {
    "etag": "W/\"7233f1c07876c5d7cd9b63234235be62\"",
    "lastModified": "Thu, 07 May 2026 05:20:16 GMT",
    "updatedAt": "2026-05-07T19:36:11+09:00"
  },
  "https://oilgas-info.jogmec.go.jp/rsslist/report_all.xml": {
    "etag": "\"1700-64c02d470b69a\"",
    "lastModified": "Mon, 02 Mar 2026 04:14:58 GMT",
    "updatedAt": "2026-03-02T15:00:42+09:00"
  },
  "https://www.customs.go.jp/news.rss": {
    "etag": "",
    "lastModified": "Thu, 07 May 2026 00:00:32 GMT",
    "updatedAt": "2026-05-07T19:36:12+09:00"
  },
  "https://assets.wor.jp/rss/rdf/bloomberg/opinion.rdf": {
    "etag": "W/\"cd85177c5e1af60a22bca2f43c30c2e0\"",
    "lastModified": "Thu, 07 May 2026 10:12:23 GMT",
    "updatedAt": "2026-05-07T19:36:12+09:00"
  },
  "https://assets.wor.jp/rss/rdf/bloomberg/economics.rdf": {
    "etag": "W/\"6320ec330b8cc5a61316bac14f69cbf6\"",
    "lastModified": "Thu, 07 May 2026 10:10:50 GMT",
    "updatedAt": "2026-05-07T19:36:13+09:00"
  },
  "https://assets.wor.jp/rss/rdf/bloomberg/technology.rdf": {
    "etag": "W/\"37ee3f4eb78d4b57570ca4a5e7e8cc7e\"",
    "lastModified": "Thu, 07 May 2026 09:13:57 GMT",
    "updatedAt": "2026-05-07T19:36:13+09:00"
  },
  "https://assets.wor.jp/rss/rdf/bloomberg/companies.rdf": {
    "etag": "W/\"bc88d4661da395a10463d022dc4a2586\"",
    "lastModified": "Thu, 07 May 2026 10:13:32 GMT",
    "updatedAt": "2026-05-07T19:36:14+09:00"
  },
  "https://assets.wor.jp/rss/rdf/bloomberg/international.rdf": {
    "etag": "W/\"dbd164f220b50d8ac360efec695d3461\"",
    "lastModified": "Thu, 07 May 2026 10:11:15 GMT",
    "updatedAt": "2026-05-07T19:36:15+09:00"
  },
  "https://assets.wor.jp/rss/rdf/bloomberg/finance.rdf": {
    "etag": "W/\"2e087eaea107c9869f7a17ae3fd47bd7\"",
    "lastModified": "Thu, 07 May 2026 10:12:35 GMT",
    "updatedAt": "2026-05-07T19:36:15+09:00"
  },
  "https://assets.wor.jp/rss/rdf/bloomberg/markets.rdf": {
    "etag": "W/\"0b1f22cb913d5ff8b5b9c16a92c5fbcc\"",
    "lastModified": "Thu, 07 May 2026 10:14:53 GMT",
    "updatedAt": "2026-05-07T19:36:15+09:00"
  },
  "https://assets.wor.jp/rss/rdf/reuters/opinion.rdf": {
    "etag": "W/\"90cc17e6960b5952f22a64c64f1ef5d8\"",
    "lastModified": "Thu, 07 May 2026 10:13:49 GMT",
    "updatedAt": "2026-05-07T19:36:16+09:00"
  },
  "https://assets.wor.jp/rss/rdf/reuters/business.rdf": {
    "etag": "W/\"67d980ae65ef610c0b0f59e0ddd9b6c1\"",
    "lastModified": "Thu, 07 May 2026 09:12:11 GMT",
    "updatedAt": "2026-05-07T19:36:16+09:00"
  },
  "https://assets.wor.jp/rss/rdf/reuters/economy.rdf": {
    "etag": "W/\"716b8f02bdab95ad5b68bac44fe3aea3\"",
    "lastModified": "Thu, 07 May 2026 10:13:21 GMT",
    "updatedAt": "2026-05-07T19:36:17+09:00"
  },
  "https://assets.wor.jp/rss/rdf/reuters/markets.rdf": {
    "etag": "W/\"94c985deca23cb30f3638cb390981031\"",
    "lastModified": "Thu, 07 May 2026 10:12:05 GMT",
    "updatedAt": "2026-05-07T19:36:18+09:00"
  },
  "https://assets.wor.jp/rss/rdf/reuters/world.rdf": {
    "etag": "W/\"25a45ea410b96b69e8694d7d5f64b570\"",
    "lastModified": "Thu, 07 May 2026 10:10:38 GMT",
    "updatedAt": "2026-05-07T19:36:18+09:00"
  },
  "https://assets.wor.jp/rss/rdf/reuters/top.rdf": {
    "etag": "W/\"f96e753740afc5f0206c6f3a50cff113\"",
    "lastModified": "Thu, 07 May 2026 10:11:27 GMT",
    "updatedAt": "2026-05-07T19:36:19+09:00"
  },
  "https://www.cao.go.jp/rss/news.rdf": {
    "etag": "W/\"1953-651346c31f32c\"",
    "lastModified": "Thu, 07 May 2026 06:30:55 GMT",
    "updatedAt": "2026-05-07T19:36:21+09:00"
  },
  "https://www.mof.go.jp/rss/index.xml": {
    "etag": "\"4d71-61c7f0b897cb3\"",
    "lastModified": "Fri, 05 Jul 2024 12:17:20 GMT",
    "updatedAt": "2026-03-05T01:07:36+09:00"
  },
  "https://earthquake.usgs.gov/earthquakes/feed/v1.0/summary/all_hour.atom": {
    "etag": "",
    "lastModified": "Thu, 07 May 2026 10:35:29 GMT",
    "updatedAt": "2026-05-07T19:36:21+09:00"
  },
  "https://www.eia.gov/rss/todayinenergy.xml": {
    "etag": "\"07176658edcdc1:0\"",
    "lastModified": "Tue, 05 May 2026 12:55:06 GMT",
    "updatedAt": "2026-05-07T19:36:21+09:00"
  },
  "https://www.gdacs.org/xml/rss.xml": {
    "etag": "W/\"9cc35f2bddedc1:0\"",
    "lastModified": "Thu, 07 May 2026 10:35:05 GMT",
    "updatedAt": "2026-05-07T19:36:23+09:00"
  },
  "https://www.freightwaves.com/rss": {
    "etag": "\"5641bbb2c987ef659f7688264b8fcc85\"",
    "lastModified": "Thu, 07 May 2026 00:27:41 GMT",
    "updatedAt": "2026-05-07T19:36:24+09:00"
  },
  "https://www.supplychaindive.com/feeds/news/": {
    "etag": "",
    "lastModified": "Wed, 06 May 2026 19:45:00 GMT",
    "updatedAt": "2026-05-07T19:36:24+09:00"
  },
  "https://www.digitimes.com/rss/daily.xml": {
    "etag": "W/\"2bfbea478dedc1:0\"",
    "lastModified": "Thu, 07 May 2026 10:00:06 GMT",
    "updatedAt": "2026-05-07T19:36:25+09:00"
  },
  "https://www.eetimes.com/feed/": {
    "etag": "W/\"af4759a058dbcbb57e433a3cb99a58a8\"",
    "lastModified": "Sat, 28 Mar 2026 11:30:11 GMT",
    "updatedAt": "2026-03-29T10:04:17+09:00"
  },
  "https://semiengineering.com/feed/": {
    "etag": "W/\"de9130ceac703ee8afab0e89a5da6c3f\"",
    "lastModified": "Thu, 07 May 2026 07:38:21 GMT",
    "updatedAt": "2026-05-07T19:36:29+09:00"
  },
  "https://www.fca.org.uk/news/rss.xml": {
    "etag": "W/\"1778148777\"",
    "lastModified": "Thu, 07 May 2026 10:12:57 GMT",
    "updatedAt": "2026-05-07T19:36:29+09:00"
  },
  "https://www.gov.uk/government/organisations/export-control-joint-unit.atom": {
    "etag": "W/\"c0f9b5989637e9ea1d29eda9581107fe\"",
    "lastModified": "",
    "updatedAt": "2026-05-07T19:36:31+09:00"
  },
  "https://agenciabrasil.ebc.com.br/rss.xml": {
    "etag": "\"1772981377-1\"",
    "lastModified": "Sun, 08 Mar 2026 14:49:37 GMT",
    "updatedAt": "2026-03-08T23:57:05+09:00"
  },
  "https://www.spa.gov.sa/rss.xml": {
    "etag": "\"ff7df7-0bbeb2504418\"",
    "lastModified": "",
    "updatedAt": "2026-03-08T23:57:27+09:00"
  },
  "https://www.gov.sg/rss/": {
    "etag": "W/\"4728eea38e81188bec69882cd30eeef4\"",
    "lastModified": "Fri, 06 Mar 2026 09:23:30 GMT",
    "updatedAt": "2026-03-08T22:22:32+09:00"
  },
  "https://www.gov.uk/government/organisations/department-for-transport.atom": {
    "etag": "W/\"b17328116d1a35e1aa014e780e1634a8\"",
    "lastModified": "",
    "updatedAt": "2026-05-07T19:36:31+09:00"
  },
  "https://www.euronews.com/rss": {
    "etag": "\"82ad4b940847e3026c11d4c10fc6becb\"",
    "lastModified": "Thu, 07 May 2026 10:31:06 GMT",
    "updatedAt": "2026-05-07T19:36:31+09:00"
  },
  "https://www.mof.go.jp/news.rss": {
    "etag": "\"7552-651378386e0e0\"",
    "lastModified": "Thu, 07 May 2026 10:12:11 GMT",
    "updatedAt": "2026-05-07T19:36:32+09:00"
  }
}